PyHyperparameterSpace/__init__.py
PyHyperparameterSpace/configuration.py
PyHyperparameterSpace/space.py
PyHyperparameterSpace/dist/__init__.py
PyHyperparameterSpace/dist/abstract_dist.py
PyHyperparameterSpace/dist/categorical.py
PyHyperparameterSpace/dist/continuous.py
PyHyperparameterSpace/hp/__init__.py
PyHyperparameterSpace/hp/abstract_hp.py
PyHyperparameterSpace/hp/categorical.py
PyHyperparameterSpace/hp/constant.py
PyHyperparameterSpace/hp/continuous.py
PyHyperparameterSpace-0.0.2.dist-info/LICENSE
PyHyperparameterSpace-0.0.2.dist-info/METADATA
PyHyperparameterSpace-0.0.2.dist-info/WHEEL
PyHyperparameterSpace-0.0.2.dist-info/top_level.txt
PyHyperparameterSpace-0.0.2.dist-info/RECORD
