Metadata-Version: 2.1
Name: PyHyperparameterSpace
Version: 0.0.2
Home-page: https://github.com/nobodyPerfecZ/py-hyperparameterspace
Author: Dennis J.
Requires-Python: >=3.10
License-File: LICENSE
Requires-Dist: numpy
Requires-Dist: PyYAML
